LICENSE
MANIFEST.in
README.md
VERSION
setup.py
src/roda/Context.py
src/roda/MongoDataProvider.py
src/roda/__init__.py
src/roda/abstracts.py
src/roda/run.py
src/roda.egg-info/PKG-INFO
src/roda.egg-info/SOURCES.txt
src/roda.egg-info/dependency_links.txt
src/roda.egg-info/requires.txt
src/roda.egg-info/top_level.txt
test/test_mock_data_provider.py
test/test_roda.py
test/test_strategy_aroon.py
test/test_strategy_dmi.py
test/test_strategy_kd.py