Metadata-Version: 1.0
Name: roda
Version: 0.1.23
Summary: ...
Home-page: UNKNOWN
Author: x6doooo
Author-email: x6doooo@gmail.com
License: MIT
Platform: UNKNOWN
